__init__.py
mcp_fileparser.py
mcp_fileparser-0.1.3.dist-info/METADATA
mcp_fileparser-0.1.3.dist-info/WHEEL
mcp_fileparser-0.1.3.dist-info/entry_points.txt
mcp_fileparser-0.1.3.dist-info/top_level.txt
mcp_fileparser-0.1.3.dist-info/RECORD
