Metadata-Version: 2.4
Name: mcp-fileparser
Version: 0.1.3
Summary: A file parser using Kimi AI
Author-email: MicLon <jcnd@163.com>
License: MIT
Project-URL: Homepage, https://github.com/mic1on/mcp-fileparser
Project-URL: Bug Tracker, https://github.com/mic1on/mcp-fileparser/issues
Keywords: mcp,fileparser
Classifier: Development Status :: 3 - Alpha
Classifier: Intended Audience :: Developers
Classifier: License :: OSI Approved :: MIT License
Classifier: Programming Language :: Python :: 3
Classifier: Programming Language :: Python :: 3.9
Classifier: Programming Language :: Python :: 3.10
Classifier: Programming Language :: Python :: 3.11
Classifier: Programming Language :: Python :: 3.12
Requires-Python: >=3.9
Requires-Dist: fastmcp>=2.12.3
Requires-Dist: httpx[socks]>=0.28.1
Requires-Dist: python-dotenv
Requires-Dist: openai
